mkdocs_spellcheck-1.1.2.dist-info/METADATA
mkdocs_spellcheck-1.1.2.dist-info/WHEEL
mkdocs_spellcheck-1.1.2.dist-info/entry_points.txt
mkdocs_spellcheck-1.1.2.dist-info/licenses/LICENSE
mkdocs_spellcheck/__init__.py
mkdocs_spellcheck/_internal/__init__.py
mkdocs_spellcheck/_internal/backends/__init__.py
mkdocs_spellcheck/_internal/backends/codespell.py
mkdocs_spellcheck/_internal/backends/symspellpy.py
mkdocs_spellcheck/_internal/debug.py
mkdocs_spellcheck/_internal/plugin.py
mkdocs_spellcheck/_internal/words.py
mkdocs_spellcheck/backends/__init__.py
mkdocs_spellcheck/backends/codespell.py
mkdocs_spellcheck/backends/symspellpy.py
mkdocs_spellcheck/plugin.py
mkdocs_spellcheck/py.typed
mkdocs_spellcheck/words.py
mkdocs_spellcheck-1.1.2.dist-info/RECORD
