Metadata-Version: 2.4
Name: mkdocs-spellcheck
Version: 1.1.2
Summary: A spell checker plugin for MkDocs.
Author-Email: =?utf-8?q?Timoth=C3=A9e_Mazzucotelli?= <dev@pawamoy.fr>
License-Expression: ISC
License-File: LICENSE
Classifier: Development Status :: 4 - Beta
Classifier: Intended Audience :: Developers
Classifier: Programming Language :: Python
Classifier: Programming Language :: Python :: 3
Classifier: Programming Language :: Python :: 3 :: Only
Classifier: Programming Language :: Python :: 3.9
Classifier: Programming Language :: Python :: 3.10
Classifier: Programming Language :: Python :: 3.11
Classifier: Programming Language :: Python :: 3.12
Classifier: Programming Language :: Python :: 3.13
Classifier: Programming Language :: Python :: 3.14
Classifier: Topic :: Documentation
Classifier: Topic :: Software Development
Classifier: Topic :: Software Development :: Documentation
Classifier: Topic :: Utilities
Classifier: Typing :: Typed
Project-URL: Homepage, https://pawamoy.github.io/mkdocs-spellcheck
Project-URL: Documentation, https://pawamoy.github.io/mkdocs-spellcheck
Project-URL: Changelog, https://pawamoy.github.io/mkdocs-spellcheck/changelog
Project-URL: Repository, https://github.com/pawamoy/mkdocs-spellcheck
Project-URL: Issues, https://github.com/pawamoy/mkdocs-spellcheck/issues
Project-URL: Discussions, https://github.com/pawamoy/mkdocs-spellcheck/discussions
Project-URL: Gitter, https://gitter.im/mkdocs-spellcheck/community
Project-URL: Funding, https://github.com/sponsors/pawamoy
Requires-Python: >=3.9
Requires-Dist: mkdocs>=1.5
Provides-Extra: all
Requires-Dist: mkdocs-spellcheck[codespell,symspellpy]; extra == "all"
Provides-Extra: codespell
Requires-Dist: codespell>=2.2.2; extra == "codespell"
Provides-Extra: symspellpy
Requires-Dist: symspellpy>=6.7.6; extra == "symspellpy"
Requires-Dist: importlib-resources>=6.4; python_version < "3.9" and extra == "symspellpy"
